archeo/__init__.py
archeo/__main__.py
archeo/constants.py
archeo/core/__init__.py
archeo/core/forward/__init__.py
archeo/core/forward/bayes_factor.py
archeo/core/forward/resampler/__init__.py
archeo/core/forward/resampler/assume_independence.py
archeo/core/forward/resampler/base.py
archeo/core/forward/resampler/generic.py
archeo/core/forward/resampler/interface.py
archeo/core/mahapatra.py
archeo/core/prior.py
archeo/core/simulator.py
archeo/env.py
archeo/frontend/__init__.py
archeo/frontend/app.py
archeo/frontend/viz.py
archeo/logger.py
archeo/preset/__init__.py
archeo/preset/agnostic.py
archeo/preset/bh1g.py
archeo/preset/quick.py
archeo/py.typed
archeo/schema.py
archeo/ui.py
archeo/utils/__init__.py
archeo/utils/file.py
archeo/utils/helper.py
archeo/utils/math.py
archeo/utils/parallel.py
archeo/version.py
archeo/visualization/__init__.py
archeo/visualization/animation.py
archeo/visualization/base.py
archeo/visualization/distribution.py
archeo/visualization/estimation.py
archeo-1.9.6.dist-info/METADATA
archeo-1.9.6.dist-info/WHEEL
archeo-1.9.6.dist-info/RECORD
