Metadata-Version: 2.3
Name: archeo
Version: 1.9.6
Summary: Bayesian framework for inferring natal kick, ancestral masses and spins of black holes.
License: MIT
Keywords: black-holes,gravitational-waves,black-hole-archeology
Author: wyhwong
Author-email: wyhwong@link.cuhk.edu.hk
Requires-Python: >=3.11,<4.0
Classifier: License :: OSI Approved :: MIT License
Classifier: Intended Audience :: Science/Research
Classifier: Natural Language :: English
Classifier: Operating System :: OS Independent
Classifier: Programming Language :: Python :: 3
Classifier: Topic :: Scientific/Engineering :: Astronomy
Classifier: Topic :: Scientific/Engineering :: Physics
Classifier: Topic :: Software Development :: Libraries :: Python Modules
Provides-Extra: ui
Requires-Dist: click (>=8.2.1,<9.0.0)
Requires-Dist: corner (>=2.2.3,<3.0.0)
Requires-Dist: gwsurrogate (>=0.8,<0.9)
Requires-Dist: matplotlib (>=3.10.3,<4.0.0)
Requires-Dist: mpl-scatter-density (>=0.8,<0.9)
Requires-Dist: nbformat (>=5.10.4,<6.0.0) ; extra == "ui"
Requires-Dist: numpy (>=2.2.6,<3.0.0)
Requires-Dist: pandas (>=2.2.3,<3.0.0)
Requires-Dist: plotly (>=6.1.2,<7.0.0) ; extra == "ui"
Requires-Dist: scipy (>=1.15.3,<1.17.0)
Requires-Dist: seaborn (>=0.13.2,<0.14.0)
Requires-Dist: streamlit (>=1.45.1,<2.0.0) ; extra == "ui"
Requires-Dist: surfinbh (>=1.2.6,<2.0.0)
Requires-Dist: tabulate (>=0.9.0,<0.10.0)
Requires-Dist: tqdm (>=4.67.1,<5.0.0)
Project-URL: Homepage, https://pypi.org/project/archeo/
Project-URL: Repository, https://github.com/wyhwong/archeo
